README.rst
pyproject.toml
setup.cfg
setup.py
src/crosslab/soa_services/parameter/__init__.py
src/crosslab/soa_services/parameter/messages.py
src/crosslab/soa_services/parameter/parameter_service.py
src/crosslab/soa_services/parameter/py.typed
src/crosslab_soa_service_parameter.egg-info/PKG-INFO
src/crosslab_soa_service_parameter.egg-info/SOURCES.txt
src/crosslab_soa_service_parameter.egg-info/dependency_links.txt
src/crosslab_soa_service_parameter.egg-info/requires.txt
src/crosslab_soa_service_parameter.egg-info/top_level.txt
tests/test_standard.py